dfa/__init__.py
dfa/dfa.py
dfa/draw.py
dfa/utils.py
dfa-4.7.1.dist-info/LICENSE
dfa-4.7.1.dist-info/METADATA
dfa-4.7.1.dist-info/WHEEL
dfa-4.7.1.dist-info/RECORD
