Metadata-Version: 2.1
Name: dfa
Version: 4.7.1
Summary: Python library for modeling DFAs, Moore Machines, and Transition Systems.
Home-page: https://github.com/mvcisback/dfa
License: MIT
Author: Marcell Vazquez-Chanlatte
Author-email: marcell.vc@eecs.berkeley.edu
Requires-Python: >=3.9,<4.0
Classifier: License :: OSI Approved :: MIT License
Classifier: Programming Language :: Python :: 3
Classifier: Programming Language :: Python :: 3.9
Classifier: Programming Language :: Python :: 3.10
Classifier: Programming Language :: Python :: 3.11
Classifier: Programming Language :: Python :: 3.12
Provides-Extra: draw
Requires-Dist: attrs (>=22)
Requires-Dist: bidict (>=0.22)
Requires-Dist: bitarray (>=2.4.0,<3.0.0)
Requires-Dist: funcy (>=1,<3)
Requires-Dist: pydot (>=1.4) ; extra == "draw"
Project-URL: Repository, https://github.com/mvcisback/dfa
